LineDream/__init__.py
LineDream/__main__.py
LineDream/__version__.py
LineDream/environment/Canvas.py
LineDream/environment/Tweaks.py
LineDream/environment/__init__.py
LineDream/helpers/CircleMath.py
LineDream/helpers/__init__.py
LineDream/primitives/BaseShape.py
LineDream/primitives/Ellipse.py
LineDream/primitives/Group.py
LineDream/primitives/Line.py
LineDream/primitives/Rectangle.py
LineDream/primitives/Text.py
LineDream/primitives/TextLine.py
LineDream/primitives/__init__.py
LineDream/primitives/hershey/__init__.py
LineDream/primitives/hershey/hershey.py
LineDream/primitives/hershey/hershey_v3.py
LineDream/primitives/hershey/aux_hershey/__init__.py
LineDream/primitives/hershey/aux_hershey/hersheydata.py
LineDream/primitives/hershey/aux_hershey/inkex.py
LineDream/primitives/hershey/aux_hershey/simplestyle.py
linedream-0.3.15.dist-info/METADATA
linedream-0.3.15.dist-info/WHEEL
linedream-0.3.15.dist-info/top_level.txt
linedream-0.3.15.dist-info/RECORD
