Metadata-Version: 2.4
Name: LineDream
Version: 0.3.15
Summary: A generative art library
Author-email: Marc Leonard <marc.r.leonard@gmail.com>
License-Expression: MIT
Project-URL: Homepage, https://linedream.marcrleonard.com
Project-URL: Documentation, https://linedream.marcrleonard.com/documentation/
Project-URL: Repository, https://github.com/marcrleonard/LineDream
Requires-Python: >=3.9
Requires-Dist: drawSvg[all]~=2.4.0
Requires-Dist: numpy>=1.24.0
Requires-Dist: lxml>=4.9.3
Requires-Dist: pillow>=10.4.0
Requires-Dist: vpype~=1.13
Requires-Dist: beautifulsoup4~=4.12.0
Provides-Extra: dev
Requires-Dist: coverage~=7.0; extra == "dev"
Requires-Dist: pytest~=7.4.0; extra == "dev"
Requires-Dist: pdoc==8.0.1; extra == "dev"
Requires-Dist: Jinja2==3.0.3; extra == "dev"
